platts_sdk/__init__.py
platts_sdk/market_data.py
platts_sdk/tok.py
platts_sdk-0.3.12.dist-info/WHEEL
platts_sdk-0.3.12.dist-info/METADATA
platts_sdk-0.3.12.dist-info/RECORD
