Metadata-Version: 2.1
Name: platts-sdk
Version: 0.3.12
Summary: 
Author: Your Name
Author-email: you@example.com
Requires-Python: >=3.7.1,<4.0.0
Classifier: Programming Language :: Python :: 3
Classifier: Programming Language :: Python :: 3.10
Classifier: Programming Language :: Python :: 3.8
Classifier: Programming Language :: Python :: 3.9
Requires-Dist: black (>=22.10.0,<23.0.0)
Requires-Dist: cachetools (==4.2.4)
Requires-Dist: pandas (==1.3.5)
Requires-Dist: requests (>=2.28.1,<3.0.0)
